Workbook

Sheet 📊 Dashboard
B2: 💰 CONTROLE FINANCEIRO INTELIGENTE 2026 - VERSÃO PRO
B3: Resumo automático de receitas, despesas e saldo atual | Atualizado em tempo real
B5: TOTAL RECEITAS | D5: TOTAL DESPESAS | F5: SALDO RESTANTE | H5: % ECONOMIZADA
B6: =SUMIF(Lancamentos!C5:C100, "Receita", Lancamentos!G5:G100) | D6: =SUMIF(Lancamentos!C5:C100, "Despesa", Lancamentos!G5:G100) | F6: =B6-D6 | H6: =IF(B6>0, F6/B6, 0)
B9: 📌 DESPESAS POR CATEGORIA
B10: Categoria | C10: Valor Total | D10: % do Gasto
B11: Moradia | C11: =SUMIFS(Lancamentos!$G$5:$G$100, Lancamentos!$C$5:$C$100, "Despesa", Lancamentos!$D$5:$D$100, B11) | D11: =IF($D$6>0, C11/$D$6, 0)
B12: Alimentação | C12: =SUMIFS(Lancamentos!$G$5:$G$100, Lancamentos!$C$5:$C$100, "Despesa", Lancamentos!$D$5:$D$100, B12) | D12: =IF($D$6>0, C12/$D$6, 0)
B13: Transporte | C13: =SUMIFS(Lancamentos!$G$5:$G$100, Lancamentos!$C$5:$C$100, "Despesa", Lancamentos!$D$5:$D$100, B13) | D13: =IF($D$6>0, C13/$D$6, 0)
B14: Saúde | C14: =SUMIFS(Lancamentos!$G$5:$G$100, Lancamentos!$C$5:$C$100, "Despesa", Lancamentos!$D$5:$D$100, B14) | D14: =IF($D$6>0, C14/$D$6, 0)
B15: Lazer | C15: =SUMIFS(Lancamentos!$G$5:$G$100, Lancamentos!$C$5:$C$100, "Despesa", Lancamentos!$D$5:$D$100, B15) | D15: =IF($D$6>0, C15/$D$6, 0)
B16: Educação | C16: =SUMIFS(Lancamentos!$G$5:$G$100, Lancamentos!$C$5:$C$100, "Despesa", Lancamentos!$D$5:$D$100, B16) | D16: =IF($D$6>0, C16/$D$6, 0)
B17: Assinaturas & Serviços | C17: =SUMIFS(Lancamentos!$G$5:$G$100, Lancamentos!$C$5:$C$100, "Despesa", Lancamentos!$D$5:$D$100, B17) | D17: =IF($D$6>0, C17/$D$6, 0)
B18: Outros | C18: =SUMIFS(Lancamentos!$G$5:$G$100, Lancamentos!$C$5:$C$100, "Despesa", Lancamentos!$D$5:$D$100, B18) | D18: =IF($D$6>0, C18/$D$6, 0)
B19: TOTAL | C19: =SUM(C11:C18) | D19: =SUM(D11:D18)

Sheet Lancamentos
B2: REGISTRO DE RECEITAS E DESPESAS
B3: Preencha suas movimentações abaixo. Os cálculos do Dashboard atualizam automaticamente.
B4: Data | C4: Tipo | D4: Categoria | E4: Descrição | F4: Forma Pagamento | G4: Valor (R$) | H4: Status
B5: 05/03/2026 | C5: Receita | D5: Salário / Proventos | E5: Salário Mensal Principal | F5: PIX | G5: 4500 | H5: Recebido
B6: 06/03/2026 | C6: Receita | D6: Renda Extra | E6: Vendas Kiwify (Infoproduto) | F6: PIX | G6: 650 | H6: Recebido
B7: 07/03/2026 | C7: Despesa | D7: Moradia | E7: Aluguel e Condomínio | F7: Boleto | G7: 1400 | H7: Pago
B8: 08/03/2026 | C8: Despesa | D8: Alimentação | E8: Compras do Mês Supermercado | F8: Cartão de Crédito | G8: 720.5 | H8: Pago
B9: 10/03/2026 | C9: Despesa | D9: Transporte | E9: Combustível Carro | F9: Cartão de Débito | G9: 220 | H9: Pago
B10: 12/03/2026 | C10: Despesa | D10: Saúde | E10: Plano de Saúde | F10: Boleto | G10: 380 | H10: Pago
B11: 15/03/2026 | C11: Despesa | D11: Lazer | E11: Jantar Fim de Semana | F11: Cartão de Crédito | G11: 185 | H11: Pago
B12: 18/03/2026 | C12: Despesa | D12: Assinaturas & Serviços | E12: Netflix, Spotify e Internet | F12: Cartão de Crédito | G12: 175.9 | H12: Pago
B13: 20/03/2026 | C13: Despesa | D13: Educação | E13: Livros e Cursos Profissionais | F13: Cartão de Crédito | G13: 120 | H13: Pago
B14: 25/03/2026 | C14: Receita | D14: Renda Extra | E14: Consultoria Freelance | F14: PIX | G14: 400 | H14: Recebido

Sheet Cartoes
B2: CONTROLE DE CARTÕES DE CRÉDITO E FATURAS
B4: Cartão / Banco | C4: Limite Total | D4: Fatura Atual | E4: Limite Disponível | F4: Dia Fechamento | G4: Dia Vencimento
B5: Nubank Mastercard | C5: 5000 | D5: 1150 | E5: =C5-D5 | F5: 25 | G5: 5
B6: Inter Visa Gold | C6: 3500 | D6: 420.5 | E6: =C6-D6 | F6: 10 | G6: 20
B7: Itaú Click | C7: 4000 | D7: 0 | E7: =C7-D7 | F7: 15 | G7: 25

Sheet Metas
B2: METAS DE ECONOMIA E RESERVA DE EMERGÊNCIA
B4: Objetivo / Meta | C4: Valor Alvo (R$) | D4: Valor Atual (R$) | E4: Falta Guardar | F4: % Concluído | G4: Prazo
B5: Reserva de Emergência (6 meses) | C5: 15000 | D5: 6500 | E5: =C5-D5 | F5: =D5/C5 | G5: Dezembro/2026
B6: Viagem de Férias | C6: 4000 | D6: 2200 | E6: =C6-D6 | F6: =D6/C6 | G6: Julho/2026
B7: Troca de Celular / Notebook | C7: 3500 | D7: 800 | E7: =C7-D7 | F7: =D7/C7 | G7: Novembro/2026
